mirror_dict/__init__.py
mirror_dict-1.0.1.dist-info/WHEEL
mirror_dict-1.0.1.dist-info/METADATA
mirror_dict-1.0.1.dist-info/RECORD
