Metadata-Version: 2.1
Name: mirror-dict
Version: 1.0.1
Summary: A mapping that returns the key if no value is found.
Home-page: https://github.com/JacobHayes/pymiscuous/tree/master/mirror-dict
License: MIT
Author: Jacob Hayes
Author-email: jacob.r.hayes@gmail.com
Requires-Python: >=3,<4
Classifier: License :: OSI Approved :: MIT License
Classifier: Programming Language :: Python :: 3
Classifier: Programming Language :: Python :: 3.4
Classifier: Programming Language :: Python :: 3.5
Classifier: Programming Language :: Python :: 3.6
Classifier: Programming Language :: Python :: 3.7
